MANIFEST.in
README.txt
setup.py
existenz/__init__.py
existenz/app.py
existenz/globe.py
existenz/location.py
existenz/util_decorator.py
existenz/world.py
existenz.egg-info/PKG-INFO
existenz.egg-info/SOURCES.txt
existenz.egg-info/dependency_links.txt
existenz.egg-info/requires.txt
existenz.egg-info/top_level.txt