Metadata-Version: 1.0
Name: existenz
Version: 0.0.2
Summary: an existing individual
Home-page: https://github.com/neoinsanity/existenz
Author: Raul Gonzalez
Author-email: mindbender@gmail.com
License: Apache License 2.0
Platform: UNKNOWN
